minty_amqp/__init__.py
minty_amqp/client.py
minty_amqp/consumer.py
minty_amqp/py.typed
minty_amqp-4.1.2.dist-info/LICENSE
minty_amqp-4.1.2.dist-info/METADATA
minty_amqp-4.1.2.dist-info/WHEEL
minty_amqp-4.1.2.dist-info/top_level.txt
minty_amqp-4.1.2.dist-info/RECORD
