Metadata-Version: 2.1
Name: minty-amqp
Version: 4.1.2
Summary: AMQP Consumer framework for minty project
Home-page: https://gitlab.com/minty-python/minty_amqp
Author: Jesse Burger
Author-email: jesse@mintlab.nl
License: EUPL license
Keywords: minty_amqp
Platform: UNKNOWN
Classifier: Development Status :: 2 - Pre-Alpha
Classifier: Intended Audience :: Developers
Classifier: License :: OSI Approved :: European Union Public Licence 1.2 (EUPL 1.2)
Classifier: Natural Language :: English
Classifier: Programming Language :: Python :: 3.9
License-File: LICENSE
Requires-Dist: minty (>=3.0.5,~=3.0)
Requires-Dist: amqpstorm (~=2.8)
